numline_c/__init__.py
numline_c-0.0.0.dist-info/METADATA
numline_c-0.0.0.dist-info/WHEEL
numline_c-0.0.0.dist-info/top_level.txt
numline_c-0.0.0.dist-info/RECORD
