Metadata-Version: 2.4
Name: numline_c
Version: 0.0.0
Summary: Pure NumPy machine-learning toolkit (name reservation)
Author-email: liujunyi <liujunyi0702@petalmail.com>
License: MIT
Project-URL: Homepage, https://github.com/nsyhykui/numline_c
Project-URL: Repository, https://github.com/nsyhykui/numline_c.git
Project-URL: Issues, https://github.com/nsyhykui/numline_c/issues
Classifier: Development Status :: 1 - Planning
Classifier: Intended Audience :: Developers
Classifier: License :: OSI Approved :: MIT License
Classifier: Programming Language :: Python :: 3
Requires-Python: >=3.8
